CHANGES.rst
MANIFEST.in
README.rst
setup.py
sphinx_scruffy.py
sphinx_scruffy.egg-info/PKG-INFO
sphinx_scruffy.egg-info/SOURCES.txt
sphinx_scruffy.egg-info/dependency_links.txt
sphinx_scruffy.egg-info/requires.txt
sphinx_scruffy.egg-info/top_level.txt