Metadata-Version: 1.0
Name: sphinx-scruffy
Version: 1.0.0
Summary: Plug-in for Sphinx to render "scruffy" diagrams.
Home-page: UNKNOWN
Author: Paylogic International
Author-email: developers@paylogic.com
License: MIT
Keywords: sphinx scruffy diagrams documentation
Platform: UNKNOWN
